pipeline_anomaly_detection_gazprom/__init__.py
pipeline_anomaly_detection_gazprom-1.0.dist-info/LICENSE
pipeline_anomaly_detection_gazprom-1.0.dist-info/METADATA
pipeline_anomaly_detection_gazprom-1.0.dist-info/WHEEL
pipeline_anomaly_detection_gazprom-1.0.dist-info/top_level.txt
pipeline_anomaly_detection_gazprom-1.0.dist-info/RECORD
