Metadata-Version: 2.1
Name: pipeline-anomaly-detection-gazprom
Version: 1.0
Summary: Gazprom requirements for the detection threshold and accuracy of determining the size of pipeline defects.
Home-page: https://github.com/vb64/pipeline.anomaly.detection.gazprom
Author: Vitaly Bogomolov
Author-email: mail@vitaly-bogomolov.ru
Project-URL: Bug Tracker, https://github.com/vb64/pipeline.anomaly.detection.gazprom/issues
Classifier: Programming Language :: Python
Classifier: License :: OSI Approved :: MIT License
Classifier: Operating System :: OS Independent
License-File: LICENSE
